COPYING
MANIFEST.in
README.rst
buildout.cfg
pyproject.toml
requirements.txt
setup.py
version.txt
bob/__init__.py
bob.ip.stereo.egg-info/PKG-INFO
bob.ip.stereo.egg-info/SOURCES.txt
bob.ip.stereo.egg-info/dependency_links.txt
bob.ip.stereo.egg-info/entry_points.txt
bob.ip.stereo.egg-info/not-zip-safe
bob.ip.stereo.egg-info/requires.txt
bob.ip.stereo.egg-info/top_level.txt
bob/ip/__init__.py
bob/ip/stereo/__init__.py
bob/ip/stereo/calibration.py
bob/ip/stereo/camera.py
bob/ip/stereo/parameters.py
bob/ip/stereo/reproject.cpp
bob/ip/stereo/stereo.py
bob/ip/stereo/stereo_stream_filters.py
bob/ip/stereo/utils.py
bob/ip/stereo/warp_calibration.py
bob/ip/stereo/config/candy_charuco.json
bob/ip/stereo/config/charuco_calib_config.json
bob/ip/stereo/config/chessboard_calib_config.json
bob/ip/stereo/config/idiap_face_calibration.json
bob/ip/stereo/config/stereo_parameters.json
bob/ip/stereo/config/warp_config.json
bob/ip/stereo/test/__init__.py
bob/ip/stereo/test/test.py
bob/ip/stereo/test/data/bounding_box.npy
bob/ip/stereo/test/data/color.png
bob/ip/stereo/test/data/landmarks.npy
bob/ip/stereo/test/data/map_3d.npy
bob/ip/stereo/test/data/nir_left_stereo.png
bob/ip/stereo/test/data/nir_right_stereo.png
bob/ip/stereo/test/data/projected_bounding_box.npy
bob/ip/stereo/test/data/projected_image.npy
bob/ip/stereo/test/data/projected_landmarks.npy
bob/ip/stereo/test/data/reprojection_color.png
bob/ip/stereo/test/data/reprojection_depth.png
bob/ip/stereo/test/data/stream_bounding_box.npy
bob/ip/stereo/test/data/stream_landmarks.npy
bob/ip/stereo/test/data/stream_projected_bounding_box.npy
bob/ip/stereo/test/data/stream_projected_landmarks.npy
bob/ip/stereo/test/data/warp_swir_norm.png
bob/ip/stereo/test/data/warp_thermal.png
doc/api.rst
doc/calibration.rst
doc/conf.py
doc/extra-intersphinx.txt
doc/index.rst
doc/links.rst
doc/nitpick-exceptions.txt
doc/warp_calibration.rst
doc/img/bob-128x128.png
doc/img/bob-favicon.ico
doc/img/bob-logo.png
doc/img/stereo_diagram.png
doc/img/warp_calibration_corners.png