Metadata-Version: 1.1
Name: bob.ip.stereo
Version: 1.0.0
Summary: Stereo matching and image reprojection
Home-page: https://gitlab.idiap.ch/bob/bob.ip.stereo
Author: David Geissbühler
Author-email: david.geissbuhler@idiap.ch
License: GPLv3
Keywords: bob,stereo
Platform: UNKNOWN
Classifier: Framework :: Bob
Classifier: Development Status :: 4 - Beta
Classifier: Intended Audience :: Science/Research
Classifier: License :: OSI Approved :: GNU General Public License v3 (GPLv3)
Classifier: Natural Language :: English
Classifier: Programming Language :: Python
Classifier: Programming Language :: Python :: 3
Classifier: Topic :: Scientific/Engineering :: Artificial Intelligence
Classifier: Topic :: Software Development :: Libraries :: Python Modules
